anchorconnector/__init__.py
anchorconnector/__main__.py
anchorconnector/connector.py
anchorconnector/pagination.py
anchorconnector/test_pagination.py
anchorconnector-0.6.2.dist-info/LICENSE
anchorconnector-0.6.2.dist-info/METADATA
anchorconnector-0.6.2.dist-info/WHEEL
anchorconnector-0.6.2.dist-info/entry_points.txt
anchorconnector-0.6.2.dist-info/top_level.txt
anchorconnector-0.6.2.dist-info/RECORD
