Metadata-Version: 2.2
Name: anchorconnector
Version: 0.6.2
Summary: Anchor Connector for Podcast Data
Author: Open Podcast
License: MIT
License-File: LICENSE
Requires-Dist: requests
Requires-Dist: loguru
Requires-Dist: PyYAML
Requires-Dist: tenacity
Requires-Dist: myst_parser[docs]
Dynamic: author
Dynamic: description
Dynamic: description-content-type
Dynamic: license
Dynamic: requires-dist
Dynamic: summary
